anthropic_bridge/__init__.py
anthropic_bridge/__main__.py
anthropic_bridge/cache.py
anthropic_bridge/client.py
anthropic_bridge/models.py
anthropic_bridge/server.py
anthropic_bridge/transform.py
anthropic_bridge/providers/__init__.py
anthropic_bridge/providers/base.py
anthropic_bridge/providers/deepseek.py
anthropic_bridge/providers/gemini.py
anthropic_bridge/providers/grok.py
anthropic_bridge/providers/minimax.py
anthropic_bridge/providers/openai.py
anthropic_bridge/providers/qwen.py
anthropic_bridge/providers/registry.py
anthropic_bridge-0.1.1.dist-info/METADATA
anthropic_bridge-0.1.1.dist-info/WHEEL
anthropic_bridge-0.1.1.dist-info/entry_points.txt
anthropic_bridge-0.1.1.dist-info/licenses/LICENSE
anthropic_bridge-0.1.1.dist-info/RECORD
