Metadata-Version: 2.4
Name: anthropic-bridge
Version: 0.1.1
Summary: Bridge Anthropic API to OpenRouter models
License-Expression: MIT
License-File: LICENSE
Requires-Python: >=3.11
Requires-Dist: fastapi>=0.115.0
Requires-Dist: httpx>=0.28.0
Requires-Dist: uvicorn>=0.32.0
Provides-Extra: dev
Requires-Dist: mypy>=1.13.0; extra == 'dev'
Requires-Dist: ruff>=0.8.0; extra == 'dev'
Provides-Extra: test
Requires-Dist: pytest-asyncio>=0.24.0; extra == 'test'
Requires-Dist: pytest>=8.0.0; extra == 'test'
